LICENSE
README.md
setup.py
pddl_plus_parser/__init__.py
pddl_plus_parser.egg-info/PKG-INFO
pddl_plus_parser.egg-info/SOURCES.txt
pddl_plus_parser.egg-info/dependency_links.txt
pddl_plus_parser.egg-info/top_level.txt
pddl_plus_parser/exporters/__init__.py
pddl_plus_parser/exporters/domain_exporter.py
pddl_plus_parser/exporters/enhsp_output_parser.py
pddl_plus_parser/exporters/ff_output_parser.py
pddl_plus_parser/exporters/numeric_trajectory_exporter.py
pddl_plus_parser/exporters/problem_exporter.py
pddl_plus_parser/lisp_parsers/__init__.py
pddl_plus_parser/lisp_parsers/domain_parser.py
pddl_plus_parser/lisp_parsers/effects_parser.py
pddl_plus_parser/lisp_parsers/parsing_utils.py
pddl_plus_parser/lisp_parsers/pddl_parser_types.py
pddl_plus_parser/lisp_parsers/pddl_tokenizer.py
pddl_plus_parser/lisp_parsers/preconditions_parser.py
pddl_plus_parser/lisp_parsers/problem_parser.py
pddl_plus_parser/lisp_parsers/trajectory_parser.py
pddl_plus_parser/models/__init__.py
pddl_plus_parser/models/action_call.py
pddl_plus_parser/models/conditional_effect.py
pddl_plus_parser/models/grounded_effect.py
pddl_plus_parser/models/grounded_precondition.py
pddl_plus_parser/models/grounding_utils.py
pddl_plus_parser/models/numeric_symbolic_operations.py
pddl_plus_parser/models/numerical_expression.py
pddl_plus_parser/models/observation.py
pddl_plus_parser/models/pddl_action.py
pddl_plus_parser/models/pddl_domain.py
pddl_plus_parser/models/pddl_function.py
pddl_plus_parser/models/pddl_object.py
pddl_plus_parser/models/pddl_operator.py
pddl_plus_parser/models/pddl_precondition.py
pddl_plus_parser/models/pddl_predicate.py
pddl_plus_parser/models/pddl_problem.py
pddl_plus_parser/models/pddl_state.py
pddl_plus_parser/models/pddl_type.py
pddl_plus_parser/models/vocabulary_creator.py
pddl_plus_parser/multi_agent/__init__.py
pddl_plus_parser/multi_agent/common.py
pddl_plus_parser/multi_agent/multi_agent_domain_converter.py
pddl_plus_parser/multi_agent/multi_agent_problem_converter.py
pddl_plus_parser/multi_agent/multi_agent_trajectory_exporter.py
pddl_plus_parser/multi_agent/single_agent_plan_converter.py
tests/exporters_tests/__init__.py
