Metadata-Version: 2.1
Name: pddl-plus-parser
Version: 3.16.0
Summary: Parser of PDDL+ domains and problems for learning purposes
Author: Argaman Mordoch
Requires-Python: >=3.8
License-File: LICENSE
